ergo_lib_python-0.28.0.dist-info/METADATA
ergo_lib_python-0.28.0.dist-info/WHEEL
ergo_lib_python/py.typed
ergo_lib_python/sigma_protocol/__init__.pyi
ergo_lib_python/ergo_tree/__init__.pyi
ergo_lib_python/__init__.py
ergo_lib_python/chain/__init__.pyi
ergo_lib_python/__init__.pyi
ergo_lib_python/transaction/__init__.pyi
ergo_lib_python/verifier/__init__.pyi
ergo_lib_python/exceptions/__init__.pyi
ergo_lib_python/wallet/__init__.pyi
ergo_lib_python/nipopow/__init__.pyi
ergo_lib_python/multi_sig/__init__.pyi
ergo_lib_python/ergo_lib_python.cpython-38-powerpc64le-linux-gnu.so
ergo_lib_python-0.28.0.dist-info/RECORD
